[
  {
    "id": "1",
    "name": "John Doe",
    "email": "john.doe@example.com",
    "openMail": false,
    "phone": "+1 (555) 123-4567",
    "percentage": "90%",
    "designation": "Software Engineer",
    "level": "C-level",
    "contactType": "linkedin",
    "address": "Danville, California, United States - 90001"
  },
  {
    "id": "2",
    "name": "Jane Smith",
    "email": "jane.smith@example.com",
    "openMail": false,
    "phone": "+1 (555) 987-6543",
    "percentage": "70%",
    "designation": "Product Manager",
    "level": "Manager level",
    "contactType": "twitter",
    "address": "Danville, California, United States"
  },
  {
    "id": "3",
    "name": "Alice Johnson",
    "email": "alice.johnson@example.com",
    "openMail": true,
    "phone": "+1 (555) 111-2222",
    "percentage": "95%",
    "designation": "QA Analyst",
    "level": "Staff",
    "contactType": "instagram",
    "address": "Danville, California, United States"
  },
  {
    "id": "4",
    "name": "Bob Williams",
    "email": "bob.williams@example.com",
    "openMail": false,
    "phone": "+1 (555) 333-4444",
    "percentage": "60%",
    "designation": "Marketing Director",
    "level": "Director level",
    "contactType": "linkedin",
    "address": "Danville, California, United States"
  },
  {
    "id": "5",
    "name": "David Miller",
    "email": "david.miller@example.com",
    "openMail": false,
    "phone": "+1 (555) 555-5555",
    "percentage": "50%",
    "designation": "Financial Analyst",
    "level": "VP level",
    "contactType": "instagram",
    "address": "Danville, California, United States"
  },
  {
    "id": "6",
    "name": "Emma Davis",
    "email": "emma.davis@example.com",
    "openMail": false,
    "phone": "+1 (555) 777-8888",
    "percentage": "30%",
    "designation": "HR Manager",
    "level": "Manager level",
    "contactType": "linkedin",
    "address": "Danville, California, United States"
  },
  {
    "id": "7",
    "name": "Frank Wilson",
    "email": "frank.wilson@example.com",
    "openMail": false,
    "phone": "+1 (555) 999-0000",
    "percentage": "90%",
    "designation": "Software Developer",
    "level": "Staff",
    "contactType": "linkedin",
    "address": "Danville, California, United States"
  },
  {
    "id": "8",
    "name": "Grace Turner",
    "email": "grace.turner@example.com",
    "openMail": true,
    "phone": "+1 (555) 111-2222",
    "percentage": "90%",
    "designation": "Sales Manager",
    "level": "Manager level",
    "contactType": "instagram",
    "address": "Danville, California, United States"
  },
  {
    "id": "9",
    "name": "Henry Clark",
    "email": "henry.clark@example.com",
    "openMail": false,
    "phone": "+1 (555) 333-4444",
    "percentage": "50%",
    "designation": "IT Director",
    "contactType": "instagram",
    "level": "Director level",
    "address": "Danville, California, United States"
  },
  {
    "id": "10",
    "name": "Isabel Garcia",
    "email": "isabel.garcia@example.com",
    "openMail": false,
    "phone": "+1 (555) 555-5555",
    "percentage": "90%",
    "designation": "Marketing Coordinator",
    "level": "Staff",
    "contactType": "instagram",
    "address": "Danville, California, United States"
  },
  {
    "id": "11",
    "name": "Jack Turner",
    "email": "jack.turner@example.com",
    "openMail": true,
    "phone": "+1 (555) 777-8888",
    "percentage": "90%",
    "designation": "Project Manager",
    "level": "Manager level",
    "contactType": "linkedin",
    "address": "Danville, California, United States"
  },
  {
    "id": "12",
    "name": "Karen White",
    "email": "karen.white@example.com",
    "openMail": false,
    "phone": "+1 (555) 999-0000",
    "percentage": "90%",
    "designation": "Finance Manager",
    "level": "Manager level",
    "contactType": "linkedin",
    "address": "Danville, California, United States"
  },
  {
    "id": "13",
    "name": "Liam Harris",
    "email": "liam.harris@example.com",
    "openMail": false,
    "phone": "+1 (555) 111-2222",
    "percentage": "90%",
    "designation": "Software Engineer",
    "level": "C-level",
    "contactType": "instagram",
    "address": "Danville, California, United States"
  },
  {
    "id": "14",
    "name": "Mia Martin",
    "email": "mia.martin@example.com",
    "openMail": true,
    "phone": "+1 (555) 333-4444",
    "percentage": "90%",
    "designation": "HR Specialist",
    "level": "Staff",
    "contactType": "twitter",
    "address": "Danville, California, United States"
  },
  {
    "id": "15",
    "name": "Nathan Lewis",
    "email": "nathan.lewis@example.com",
    "openMail": true,
    "phone": "+1 (555) 555-5555",
    "percentage": "90%",
    "designation": "Product Owner",
    "level": "Director level",
    "contactType": "linkedin",
    "address": "Danville, California, United States"
  },
  {
    "id": "16",
    "name": "Olivia Turner",
    "email": "olivia.turner@example.com",
    "openMail": false,
    "phone": "+1 (555) 777-8888",
    "percentage": "90%",
    "designation": "Customer Support",
    "level": "Staff",
    "contactType": "linkedin",
    "address": "Danville, California, United States"
  },
  {
    "id": "17",
    "name": "Peter Harris",
    "email": "peter.harris@example.com",
    "openMail": false,
    "phone": "+1 (555) 999-0000",
    "percentage": "90%",
    "designation": "Marketing Specialist",
    "level": "Staff",
    "contactType": "instagram",
    "address": "Danville, California, United States"
  },
  {
    "id": "18",
    "name": "Quinn Taylor",
    "email": "quinn.taylor@example.com",
    "openMail": true,
    "phone": "+1 (555) 111-2222",
    "percentage": "90%",
    "designation": "IT Specialist",
    "level": "Staff",
    "contactType": "linkedin",
    "address": "Danville, California, United States"
  },
  {
    "id": "19",
    "name": "Rachel Adams",
    "email": "rachel.adams@example.com",
    "openMail": false,
    "phone": "+1 (555) 333-4444",
    "percentage": "90%",
    "designation": "Sales Representative",
    "level": "Staff",
    "contactType": "twitter",
    "address": "Danville, California, United States"
  },
  {
    "id": "20",
    "name": "Samuel Turner",
    "email": "samuel.turner@example.com",
    "openMail": false,
    "phone": "+1 (555) 555-5555",
    "percentage": "90%",
    "designation": "Business Analyst",
    "level": "Manager level",
    "contactType": "linkedin",
    "address": "Danville, California, United States"
  },
  {
    "id": "21",
    "name": "Tina Roberts",
    "email": "tina.roberts@example.com",
    "openMail": true,
    "phone": "+1 (555) 777-8888",
    "percentage": "90%",
    "designation": "Graphic Designer",
    "level": "Staff",
    "contactType": "instagram",
    "address": "Danville, California, United States"
  },
  {
    "id": "22",
    "name": "Ulysses Walker",
    "email": "ulysses.walker@example.com",
    "openMail": false,
    "phone": "+1 (555) 999-0000",
    "percentage": "90%",
    "designation": "Operations Manager",
    "level": "Manager level",
    "contactType": "linkedin",
    "address": "Danville, California, United States"
  },
  {
    "id": "23",
    "name": "Victoria Turner",
    "email": "victoria.turner@example.com",
    "openMail": true,
    "phone": "+1 (555) 111-2222",
    "percentage": "90%",
    "designation": "Quality Assurance",
    "level": "Staff",
    "contactType": "linkedin",
    "address": "Danville, California, United States"
  },
  {
    "id": "24",
    "name": "William Harris",
    "email": "william.harris@example.com",
    "openMail": false,
    "phone": "+1 (555) 333-4444",
    "percentage": "90%",
    "designation": "Technical Writer",
    "level": "Staff",
    "contactType": "instagram",
    "address": "Danville, California, United States"
  },
  {
    "id": "25",
    "name": "Xavier Adams",
    "email": "xavier.adams@example.com",
    "openMail": false,
    "phone": "+1 (555) 555-5555",
    "percentage": "90%",
    "designation": "Business Development",
    "level": "Manager level",
    "contactType": "linkedin",
    "address": "Danville, California, United States"
  },
  {
    "id": "26",
    "name": "Yasmine Taylor",
    "email": "yasmine.taylor@example.com",
    "openMail": true,
    "phone": "+1 (555) 777-8888",
    "percentage": "90%",
    "designation": "Customer Success",
    "level": "Manager level",
    "contactType": "instagram",
    "address": "Danville, California, United States"
  },
  {
    "id": "27",
    "name": "Zane Turner",
    "email": "zane.turner@example.com",
    "openMail": false,
    "phone": "+1 (555) 999-0000",
    "percentage": "90%",
    "designation": "Database Administrator",
    "level": "Director level",
    "contactType": "linkedin",
    "address": "Danville, California, United States"
  },
  {
    "id": "28",
    "name": "Amelia Clark",
    "email": "amelia.clark@example.com",
    "openMail": false,
    "phone": "+1 (555) 111-2222",
    "percentage": "90%",
    "designation": "UI/UX Designer",
    "level": "Staff",
    "contactType": "linkedin",
    "address": "Danville, California, United States"
  },
  {
    "id": "29",
    "name": "Benjamin White",
    "email": "benjamin.white@example.com",
    "openMail": true,
    "phone": "+1 (555) 333-4444",
    "percentage": "90%",
    "designation": "Network Engineer",
    "level": "Director level",
    "contactType": "instagram",
    "address": "Danville, California, United States"
  },
  {
    "id": "30",
    "name": "Catherine Adams",
    "email": "catherine.adams@example.com",
    "openMail": false,
    "phone": "+1 (555) 555-5555",
    "percentage": "90%",
    "designation": "Human Resources",
    "level": "Manager level",
    "contactType": "linkedin",
    "address": "Danville, California, United States"
  },
  {
    "id": "31",
    "name": "David Turner",
    "email": "david.turner@example.com",
    "openMail": false,
    "phone": "+1 (555) 777-8888",
    "percentage": "90%",
    "designation": "Data Analyst",
    "level": "Staff",
    "contactType": "twitter",
    "address": "Danville, California, United States"
  },
  {
    "id": "32",
    "name": "Eva Robinson",
    "email": "eva.robinson@example.com",
    "openMail": false,
    "phone": "+1 (555) 999-0000",
    "percentage": "90%",
    "designation": "Marketing Specialist",
    "level": "Staff",
    "contactType": "instagram",
    "address": "Danville, California, United States"
  },
  {
    "id": "33",
    "name": "Felix Harris",
    "email": "felix.harris@example.com",
    "openMail": false,
    "phone": "+1 (555) 111-2222",
    "percentage": "90%",
    "designation": "Business Analyst",
    "level": "Manager level",
    "contactType": "linkedin",
    "address": "Danville, California, United States"
  },
  {
    "id": "34",
    "name": "Grace Turner",
    "email": "grace.turner@example.com",
    "openMail": false,
    "phone": "+1 (555) 333-4444",
    "percentage": "90%",
    "designation": "Legal Counsel",
    "level": "Director level",
    "contactType": "twitter",
    "address": "Danville, California, United States"
  },
  {
    "id": "35",
    "name": "Henry Clark",
    "email": "henry.clark@example.com",
    "openMail": false,
    "phone": "+1 (555) 555-5555",
    "percentage": "90%",
    "designation": "Logistics Coordinator",
    "contactType": "instagram",
    "level": "Manager level",
    "address": "Danville, California, United States"
  },
  {
    "id": "36",
    "name": "Isabel Garcia",
    "email": "isabel.garcia@example.com",
    "openMail": false,
    "phone": "+1 (555) 777-8888",
    "percentage": "90%",
    "designation": "Research Scientist",
    "level": "Staff",
    "contactType": "linkedin",
    "address": "Danville, California, United States"
  },
  {
    "id": "37",
    "name": "Jack Turner",
    "email": "jack.turner@example.com",
    "openMail": false,
    "phone": "+1 (555) 999-0000",
    "percentage": "90%",
    "designation": "Technical Support",
    "level": "Staff",
    "contactType": "twitter",
    "address": "Danville, California, United States"
  },
  {
    "id": "38",
    "name": "Karen White",
    "email": "karen.white@example.com",
    "openMail": false,
    "phone": "+1 (555) 111-2222",
    "percentage": "90%",
    "designation": "Quality Engineer",
    "level": "Director level",
    "contactType": "linkedin",
    "address": "Danville, California, United States"
  },
  {
    "id": "39",
    "name": "Liam Harris",
    "email": "liam.harris@example.com",
    "openMail": false,
    "phone": "+1 (555) 333-4444",
    "percentage": "90%",
    "designation": "Supply Chain Manager",
    "contactType": "instagram",
    "level": "Manager level",
    "address": "Danville, California, United States"
  },
  {
    "id": "40",
    "name": "Mia Martin",
    "email": "mia.martin@example.com",
    "openMail": false,
    "phone": "+1 (555) 555-5555",
    "percentage": "90%",
    "designation": "Systems Analyst",
    "level": "Staff",
    "contactType": "twitter",
    "address": "Danville, California, United States"
  },
  {
    "id": "41",
    "name": "Nathan Lewis",
    "email": "nathan.lewis@example.com",
    "openMail": false,
    "phone": "+1 (555) 777-8888",
    "percentage": "90%",
    "designation": "UX Designer",
    "level": "Staff",
    "contactType": "linkedin",
    "address": "Danville, California, United States"
  },
  {
    "id": "42",
    "name": "Olivia Taylor",
    "email": "olivia.taylor@example.com",
    "openMail": false,
    "phone": "+1 (555) 999-0000",
    "percentage": "90%",
    "designation": "Financial Analyst",
    "level": "Manager level",
    "contactType": "instagram",
    "address": "Danville, California, United States"
  },
  {
    "id": "43",
    "name": "Peter Adams",
    "email": "peter.adams@example.com",
    "openMail": false,
    "phone": "+1 (555) 111-2222",
    "percentage": "90%",
    "designation": "HR Manager",
    "level": "Manager level",
    "contactType": "twitter",
    "address": "Danville, California, United States"
  },
  {
    "id": "44",
    "name": "Quinn Turner",
    "email": "quinn.turner@example.com",
    "openMail": false,
    "phone": "+1 (555) 333-4444",
    "percentage": "90%",
    "designation": "Operations Analyst",
    "level": "Staff",
    "contactType": "linkedin",
    "address": "Danville, California, United States"
  },
  {
    "id": "45",
    "name": "Rachel White",
    "email": "rachel.white@example.com",
    "openMail": false,
    "phone": "+1 (555) 555-5555",
    "percentage": "90%",
    "designation": "Product Manager",
    "level": "Director level",
    "contactType": "instagram",
    "address": "Danville, California, United States"
  },
  {
    "id": "46",
    "name": "Samuel Lewis",
    "email": "samuel.lewis@example.com",
    "openMail": false,
    "phone": "+1 (555) 777-8888",
    "percentage": "90%",
    "designation": "Sales Representative",
    "level": "Staff",
    "contactType": "twitter",
    "address": "Danville, California, United States"
  },
  {
    "id": "47",
    "name": "Tara Robinson",
    "email": "tara.robinson@example.com",
    "openMail": false,
    "phone": "+1 (555) 999-0000",
    "percentage": "90%",
    "designation": "Software Developer",
    "level": "Staff",
    "contactType": "linkedin",
    "address": "Danville, California, United States"
  },
  {
    "id": "48",
    "name": "Ulysses Harris",
    "email": "ulysses.harris@example.com",
    "openMail": false,
    "phone": "+1 (555) 111-2222",
    "percentage": "90%",
    "designation": "Tech Support",
    "level": "Manager level",
    "contactType": "instagram",
    "address": "Danville, California, United States"
  },
  {
    "id": "49",
    "name": "Victoria Adams",
    "email": "victoria.adams@example.com",
    "openMail": false,
    "phone": "+1 (555) 333-4444",
    "percentage": "90%",
    "designation": "UI Designer",
    "level": "Staff",
    "contactType": "twitter",
    "address": "Danville, California, United States"
  },
  {
    "id": "50",
    "name": "William Turner",
    "email": "william.turner@example.com",
    "openMail": false,
    "phone": "+1 (555) 555-5555",
    "percentage": "90%",
    "designation": "Web Developer",
    "level": "Director level",
    "contactType": "linkedin",
    "address": "Danville, California, United States"
  },
  {
    "id": "51",
    "name": "Xena White",
    "email": "xena.white@example.com",
    "openMail": false,
    "phone": "+1 (555) 777-8888",
    "percentage": "90%",
    "designation": "Systems Administrator",
    "level": "Manager level",
    "contactType": "instagram",
    "address": "Danville, California, United States"
  },
  {
    "id": "52",
    "name": "Yuri Lewis",
    "email": "yuri.lewis@example.com",
    "openMail": false,
    "phone": "+1 (555) 999-0000",
    "percentage": "90%",
    "designation": "QA Engineer",
    "level": "Staff",
    "contactType": "twitter",
    "address": "Danville, California, United States"
  },
  {
    "id": "53",
    "name": "Zara Turner",
    "email": "zara.turner@example.com",
    "openMail": false,
    "phone": "+1 (555) 111-2222",
    "percentage": "90%",
    "designation": "Marketing Manager",
    "level": "Director level",
    "contactType": "linkedin",
    "address": "Danville, California, United States"
  },
  {
    "id": "54",
    "name": "Adam Harris",
    "email": "adam.harris@example.com",
    "openMail": false,
    "phone": "+1 (555) 333-4444",
    "percentage": "90%",
    "designation": "Operations Coordinator",
    "level": "Manager level",
    "contactType": "instagram",
    "address": "Danville, California, United States"
  },
  {
    "id": "55",
    "name": "Bella Robinson",
    "email": "bella.robinson@example.com",
    "openMail": false,
    "phone": "+1 (555) 555-5555",
    "percentage": "90%",
    "designation": "Product Analyst",
    "level": "Staff",
    "contactType": "twitter",
    "address": "Danville, California, United States"
  },
  {
    "id": "56",
    "name": "Caleb Turner",
    "email": "caleb.turner@example.com",
    "openMail": false,
    "phone": "+1 (555) 777-8888",
    "percentage": "90%",
    "designation": "Technical Specialist",
    "level": "Staff",
    "contactType": "linkedin",
    "address": "Danville, California, United States"
  },
  {
    "id": "57",
    "name": "Diana White",
    "email": "diana.white@example.com",
    "openMail": false,
    "phone": "+1 (555) 999-0000",
    "percentage": "90%",
    "designation": "Financial Planner",
    "level": "Manager level",
    "contactType": "instagram",
    "address": "Danville, California, United States"
  },
  {
    "id": "58",
    "name": "Elijah Adams",
    "email": "elijah.adams@example.com",
    "openMail": false,
    "phone": "+1 (555) 111-2222",
    "percentage": "90%",
    "designation": "HR Specialist",
    "level": "Manager level",
    "contactType": "twitter",
    "address": "Danville, California, United States"
  },
  {
    "id": "59",
    "name": "Fiona Turner",
    "email": "fiona.turner@example.com",
    "openMail": false,
    "phone": "+1 (555) 333-4444",
    "percentage": "90%",
    "designation": "UX Analyst",
    "level": "Staff",
    "contactType": "linkedin",
    "address": "Danville, California, United States"
  },
  {
    "id": "60",
    "name": "Gavin Harris",
    "email": "gavin.harris@example.com",
    "openMail": false,
    "phone": "+1 (555) 555-5555",
    "percentage": "90%",
    "designation": "Software Engineer",
    "level": "Director level",
    "contactType": "instagram",
    "address": "Danville, California, United States"
  }
]
